opendatalabs_query_sdk/__init__.py
opendatalabs_query_sdk/client.py
opendatalabs_query_sdk-0.1.1.dist-info/METADATA
opendatalabs_query_sdk-0.1.1.dist-info/WHEEL
opendatalabs_query_sdk-0.1.1.dist-info/RECORD
