Metadata-Version: 2.4
Name: opendatalabs-query-sdk
Version: 0.1.1
Summary: A Python SDK for interacting with the Query API service
Project-URL: Homepage, https://github.com/vana-com/query-sdk-python
Project-URL: Documentation, https://github.com/vana-com/query-sdk-python#readme
Project-URL: Issues, https://github.com/vana-com/query-sdk-python/issues
Author-email: OpenDataLabs <alex@opendatalabs.xyz>
License-Expression: MIT
Keywords: api,query,sdk
Classifier: Development Status :: 3 - Alpha
Classifier: Intended Audience :: Developers
Classifier: License :: OSI Approved :: MIT License
Classifier: Programming Language :: Python :: 3
Classifier: Programming Language :: Python :: 3.7
Classifier: Programming Language :: Python :: 3.8
Classifier: Programming Language :: Python :: 3.9
Classifier: Programming Language :: Python :: 3.10
Classifier: Programming Language :: Python :: 3.11
Requires-Python: >=3.7
Requires-Dist: requests>=2.28.0
Requires-Dist: typing-extensions>=4.0.0; python_version < '3.8'
Provides-Extra: dev
Requires-Dist: black>=22.0.0; extra == 'dev'
Requires-Dist: build>=0.10.0; extra == 'dev'
Requires-Dist: isort>=5.0.0; extra == 'dev'
Requires-Dist: mypy>=0.990; extra == 'dev'
Requires-Dist: pytest-cov>=4.0.0; extra == 'dev'
Requires-Dist: pytest>=7.0.0; extra == 'dev'
Requires-Dist: ruff>=0.0.290; extra == 'dev'
Requires-Dist: twine>=4.0.2; extra == 'dev'
